spiratestexecute.py
spiratestextension.py
pyunit_spiratest-6.0.0.dist-info/METADATA
pyunit_spiratest-6.0.0.dist-info/WHEEL
pyunit_spiratest-6.0.0.dist-info/entry_points.txt
pyunit_spiratest-6.0.0.dist-info/top_level.txt
pyunit_spiratest-6.0.0.dist-info/RECORD
