Metadata-Version: 2.1
Name: pyunit-spiratest
Version: 6.0.0
Summary: Exports Python unit tests as test runs in Spira (SpiraTest/Team/Plan)
Home-page: http://www.inflectra.com/SpiraTest/Integrations/Unit-Test-Frameworks.aspx
Author: Inflectra Corporation
Author-email: support@inflectra.com
Classifier: Topic :: Software Development :: Testing
Classifier: Programming Language :: Python :: 3
Classifier: Operating System :: OS Independent
